Metadata-Version: 2.1
Name: gcs-oauth2-boto-plugin
Version: 2.0
Summary: Auth plugin allowing use the use of OAuth 2.0 credentials for Google Cloud Storage in the Boto library.
Home-page: https://developers.google.com/storage/docs/gspythonlibrary
Author: Google Inc.
Author-email: gs-team@google.com
License: Apache 2.0
Download-URL: https://github.com/GoogleCloudPlatform/gcs-oauth2-boto-plugin
Platform: any
Classifier: Development Status :: 7 - Inactive
Classifier: Intended Audience :: Developers
Classifier: License :: OSI Approved :: Apache Software License
Classifier: Programming Language :: Python :: 2
Classifier: Programming Language :: Python :: 2.7
Classifier: Programming Language :: Python :: 3
Classifier: Programming Language :: Python :: 3.4
Classifier: Programming Language :: Python :: 3.5
Classifier: Programming Language :: Python :: 3.6
Classifier: Topic :: Internet :: WWW/HTTP
Classifier: Topic :: Software Development :: Libraries :: Python Modules
Provides-Extra: dev
